density_calculator-0.2.1.dist-info/RECORD
density_calculator-0.2.1.dist-info/WHEEL
density_calculator-0.2.1.dist-info/METADATA
include/gemmi/binner.hpp
include/gemmi/calculate.hpp
include/gemmi/it92.hpp
include/gemmi/c4322.hpp
include/gemmi/mmdb.hpp
include/gemmi/read_map.hpp
include/gemmi/fileutil.hpp
include/gemmi/bond_idx.hpp
include/gemmi/neighbor.hpp
include/gemmi/twin.hpp
include/gemmi/utf.hpp
include/gemmi/sprintf.hpp
include/gemmi/asumask.hpp
include/gemmi/mtz2cif.hpp
include/gemmi/solmask.hpp
include/gemmi/to_cif.hpp
include/gemmi/chemcomp_xyz.hpp
include/gemmi/enumstr.hpp
include/gemmi/span.hpp
include/gemmi/floodfill.hpp
include/gemmi/json.hpp
include/gemmi/cif.hpp
include/gemmi/unitcell.hpp
include/gemmi/pdb_id.hpp
include/gemmi/monlib.hpp
include/gemmi/topo.hpp
include/gemmi/align.hpp
include/gemmi/pirfasta.hpp
include/gemmi/atof.hpp
include/gemmi/asudata.hpp
include/gemmi/dencalc.hpp
include/gemmi/polyheur.hpp
include/gemmi/numb.hpp
include/gemmi/seqid.hpp
include/gemmi/grid.hpp
include/gemmi/contact.hpp
include/gemmi/recgrid.hpp
include/gemmi/linkhunt.hpp
include/gemmi/ecalc.hpp
include/gemmi/modify.hpp
include/gemmi/reciproc.hpp
include/gemmi/read_cif.hpp
include/gemmi/model.hpp
include/gemmi/mmread.hpp
include/gemmi/riding_h.hpp
include/gemmi/metadata.hpp
include/gemmi/remarks.hpp
include/gemmi/to_mmcif.hpp
include/gemmi/eig3.hpp
include/gemmi/version.hpp
include/gemmi/smcif.hpp
include/gemmi/blob.hpp
include/gemmi/math.hpp
include/gemmi/mtz.hpp
include/gemmi/stats.hpp
include/gemmi/gz.hpp
include/gemmi/seqtools.hpp
include/gemmi/atox.hpp
include/gemmi/xds_ascii.hpp
include/gemmi/chemcomp.hpp
include/gemmi/scaling.hpp
include/gemmi/fprime.hpp
include/gemmi/cellred.hpp
include/gemmi/formfact.hpp
include/gemmi/seqalign.hpp
include/gemmi/addends.hpp
include/gemmi/interop.hpp
include/gemmi/symmetry.hpp
include/gemmi/mmread_gz.hpp
include/gemmi/neutron92.hpp
include/gemmi/ddl.hpp
include/gemmi/to_pdb.hpp
include/gemmi/cifdoc.hpp
include/gemmi/util.hpp
include/gemmi/assembly.hpp
