Metadata-Version: 2.1
Name: density-calculator
Version: 0.2.1
Summary: density_calculator: Calculate mFo-DFc density with Clipper through Gemmi!
Author-Email: Jordan Dialpuri <jordan.dialpuri@york.ac.uk>
Classifier: License :: OSI Approved :: BSD License
Project-URL: Homepage, https://github.com/Dialpuri/DensityCalculator
Requires-Python: >=3.9
Requires-Dist: gemmi
Requires-Dist: numpy
